skyscraper/__init__.py
skyscraper/cli.py
skyscraper/exceptions.py
skyscraper/results.py
skyscraper/schema.py
skyscraper/task.py
skyscraper/web_crawler.py
skyscraper-0.0.5.dist-info/METADATA
skyscraper-0.0.5.dist-info/RECORD
skyscraper-0.0.5.dist-info/WHEEL
skyscraper-0.0.5.dist-info/entry_points.txt
skyscraper-0.0.5.dist-info/top_level.txt
tests/__init__.py
tests/test_default.py
