Metadata-Version: 2.1
Name: skyscraper
Version: 0.0.5
Summary: YAML based lightweight crawlers
Home-page: https://gitlab.com/woning-group/libs/skyscraper
License: UNKNOWN
Platform: UNKNOWN
Provides-Extra: dev
Requires-Dist: woning-wattle
Requires-Dist: click
Requires-Dist: requests
Requires-Dist: beautifulsoup4
Provides-Extra: dev
Requires-Dist: woning-bricks; extra == 'dev'
